{
"skeleton": { "hash": "6EGndAzOhJ1fkmj0EGgrkOOG/S0", "spine": "3.7.92", "width": 627.25, "height": 983.88, "images": "", "audio": "D:/WeRplay/2D projects/Lost Twins/ladder old_062620/Ladder anim" },
"bones": [
	{ "name": "root" },
	{ "name": "bottom", "parent": "root", "x": -6.51, "y": 124.68 },
	{ "name": "wheel2", "parent": "bottom", "x": -121.66, "y": -49.52, "color": "ff0000ff" },
	{ "name": "wheel3", "parent": "bottom", "x": 134.7, "y": -49.25, "color": "ff0000ff" },
	{ "name": "gear-02", "parent": "bottom", "x": -113.73, "y": 15.75 },
	{ "name": "gear-3", "parent": "bottom", "x": -224.23, "y": 40.72 },
	{ "name": "top", "parent": "bottom", "x": -3.94, "y": 36 },
	{ "name": "flag", "parent": "top", "x": -87.23, "y": 770.36 },
	{ "name": "flag3", "parent": "flag", "length": 18.62, "rotation": -98.28, "x": -3.08, "y": -8.67 },
	{ "name": "flag4", "parent": "flag3", "length": 21.94, "rotation": 1.26, "x": 18.62 },
	{ "name": "flag5", "parent": "flag4", "length": 22.08, "rotation": -2.59, "x": 21.94 },
	{ "name": "flag6", "parent": "flag5", "length": 17.29, "rotation": -25.93, "x": 22.08 },
	{ "name": "flag7", "parent": "flag6", "length": 18.03, "rotation": -6.45, "x": 16.9, "y": 0.55 },
	{ "name": "flag8", "parent": "flag7", "length": 21.13, "rotation": 16.64, "x": 18.03 },
	{ "name": "1", "parent": "gear-3", "x": 4.66, "y": 4.06 },
	{ "name": "3", "parent": "1", "length": 12.7, "rotation": -123.39, "x": -3.07, "y": 0.48 },
	{ "name": "4", "parent": "3", "length": 53.77, "rotation": -54.81, "x": 12.7 },
	{ "name": "6", "parent": "4", "x": 56.41, "y": -0.32 },
	{ "name": "gear-4", "parent": "bottom", "x": 118.92, "y": 17.36 },
	{ "name": "gear-5", "parent": "bottom", "x": 223.37, "y": 40.64 },
	{ "name": "2", "parent": "gear-5", "rotation": -177, "x": 3.99, "y": -0.5, "scaleY": -1 },
	{ "name": "5", "parent": "2", "length": 12.7, "rotation": -123.39, "x": -3.07, "y": 0.48 },
	{ "name": "7", "parent": "5", "length": 53.77, "rotation": -54.81, "x": 12.7 },
	{ "name": "8", "parent": "7", "x": 56.41, "y": -0.32 },
	{ "name": "bottom_back", "parent": "bottom", "x": -18.77, "y": 39.47 }
],
"slots": [
	{ "name": "bottom_back", "bone": "bottom_back", "attachment": "bottom_back" },
	{ "name": "top", "bone": "top", "attachment": "top" },
	{ "name": "gear-3", "bone": "gear-3", "attachment": "gear-01" },
	{ "name": "gear-5", "bone": "gear-5", "attachment": "gear-01" },
	{ "name": "wheel2", "bone": "wheel2", "attachment": "wheel" },
	{ "name": "wheel3", "bone": "wheel3", "attachment": "wheel" },
	{ "name": "gear-02", "bone": "gear-02", "attachment": "gear-02" },
	{ "name": "gear-4", "bone": "gear-4", "attachment": "gear-02" },
	{ "name": "bottom", "bone": "bottom", "attachment": "bottom" },
	{ "name": "flag", "bone": "flag3", "attachment": "flag" },
	{ "name": "1", "bone": "1", "attachment": "1" },
	{ "name": "4", "bone": "2", "attachment": "1" },
	{ "name": "2", "bone": "3", "attachment": "2" },
	{ "name": "5", "bone": "5", "attachment": "2" },
	{ "name": "3", "bone": "6", "attachment": "3" },
	{ "name": "6", "bone": "8", "attachment": "3" }
],
"skins": {
	"default": {
		"1": {
			"1": { "x": -0.7, "y": 0.73, "width": 30, "height": 31 }
		},
		"2": {
			"2": {
				"type": "mesh",
				"uvs": [ 0.22347, 0.19847, 0.25128, 0.2721, 0.28642, 0.35099, 0.41231, 0.36151, 0.82953, 0.36677, 0.83246, 0.67706, 0.39914, 0.68495, 0.30691, 0.68232, 0.23225, 0.65077, 0.18102, 0.60607, 0.12539, 0.46933, 0.08147, 0.33521, 0.08733, 0.23792, 0.14149, 0.16166, 0.18687, 0.16429, 0.7477, 0.54163, 0.51683, 0.51893, 0.31981, 0.5167, 0.20593, 0.42115, 0.15917, 0.31047 ],
				"triangles": [ 6, 15, 5, 6, 16, 15, 7, 17, 6, 6, 17, 16, 7, 8, 17, 15, 4, 5, 8, 9, 17, 15, 16, 4, 17, 3, 16, 16, 3, 4, 18, 2, 17, 17, 2, 3, 9, 18, 17, 9, 10, 18, 18, 11, 19, 18, 10, 11, 2, 19, 1, 2, 18, 19, 11, 12, 19, 19, 12, 0, 19, 0, 1, 0, 13, 14, 13, 0, 12 ],
				"vertices": [ 2, 15, -0.07, -7.64, 0.98506, 16, -1.12, -14.84, 0.01494, 2, 15, 4.73, -7.62, 0.86967, 16, 1.64, -10.9, 0.13033, 2, 15, 10.17, -8.02, 0.34247, 16, 5.1, -6.69, 0.65753, 1, 16, 17.32, -6.28, 1, 1, 16, 57.79, -6.54, 1, 1, 16, 58.29, 10.21, 1, 1, 16, 16.27, 11.2, 1, 2, 15, 26.05, 0.45, 4.0E-4, 16, 7.33, 11.18, 0.9996, 2, 15, 20.55, 5.46, 0.15436, 16, 0.06, 9.57, 0.84564, 2, 15, 15.75, 8.2, 0.56247, 16, -4.94, 7.22, 0.43753, 2, 15, 6.61, 8.47, 0.99833, 16, -10.43, -0.09, 0.00167, 1, 15, -1.77, 7.89, 1, 1, 15, -5.78, 4.46, 1, 1, 15, -6.21, -2.21, 1, 2, 15, -3.6, -5.76, 0.99974, 16, -4.69, -16.64, 2.6E-4, 1, 16, 49.98, 3.01, 1, 1, 16, 27.57, 2.08, 1, 1, 16, 8.46, 2.22, 1, 1, 15, 8.88, 0.56, 1, 1, 15, 1.39, 0.92, 1 ],
				"hull": 15,
				"edges": [ 0, 2, 2, 4, 4, 6, 6, 8, 8, 10, 10, 12, 12, 14, 14, 16, 16, 18, 18, 20, 20, 22, 22, 24, 24, 26, 26, 28, 0, 28 ],
				"width": 97,
				"height": 54
			}
		},
		"3": {
			"3": { "x": 6.95, "y": 8.87, "scaleX": -0.976, "rotation": 178.2, "width": 33, "height": 35 }
		},
		"4": {
			"1": { "x": -0.7, "y": 0.73, "width": 30, "height": 31 }
		},
		"5": {
			"2": {
				"type": "mesh",
				"uvs": [ 0.22347, 0.19847, 0.25128, 0.2721, 0.28642, 0.35099, 0.41231, 0.36151, 0.82953, 0.36677, 0.83246, 0.67706, 0.39914, 0.68495, 0.30691, 0.68232, 0.23225, 0.65077, 0.18102, 0.60607, 0.12539, 0.46933, 0.08147, 0.33521, 0.08733, 0.23792, 0.14149, 0.16166, 0.18687, 0.16429, 0.7477, 0.54163, 0.51683, 0.51893, 0.31981, 0.5167, 0.20593, 0.42115, 0.15917, 0.31047 ],
				"triangles": [ 6, 15, 5, 6, 16, 15, 7, 17, 6, 6, 17, 16, 7, 8, 17, 15, 4, 5, 8, 9, 17, 15, 16, 4, 17, 3, 16, 16, 3, 4, 18, 2, 17, 17, 2, 3, 9, 18, 17, 9, 10, 18, 18, 11, 19, 18, 10, 11, 2, 19, 1, 2, 18, 19, 11, 12, 19, 19, 12, 0, 19, 0, 1, 0, 13, 14, 13, 0, 12 ],
				"vertices": [ 2, 21, -0.07, -7.64, 0.98506, 22, -1.12, -14.84, 0.01494, 2, 21, 4.73, -7.62, 0.86967, 22, 1.64, -10.9, 0.13033, 2, 21, 10.17, -8.02, 0.34247, 22, 5.1, -6.69, 0.65753, 1, 22, 17.32, -6.28, 1, 1, 22, 57.79, -6.54, 1, 1, 22, 58.29, 10.21, 1, 1, 22, 16.27, 11.2, 1, 2, 21, 26.05, 0.45, 4.0E-4, 22, 7.33, 11.18, 0.9996, 2, 21, 20.55, 5.46, 0.15436, 22, 0.06, 9.57, 0.84564, 2, 21, 15.75, 8.2, 0.56247, 22, -4.94, 7.22, 0.43753, 2, 21, 6.61, 8.47, 0.99833, 22, -10.43, -0.09, 0.00167, 1, 21, -1.77, 7.89, 1, 1, 21, -5.78, 4.46, 1, 1, 21, -6.21, -2.21, 1, 2, 21, -3.6, -5.76, 0.99974, 22, -4.69, -16.64, 2.6E-4, 1, 22, 49.98, 3.01, 1, 1, 22, 27.57, 2.08, 1, 1, 22, 8.46, 2.22, 1, 1, 21, 8.88, 0.56, 1, 1, 21, 1.39, 0.92, 1 ],
				"hull": 15,
				"edges": [ 0, 2, 2, 4, 4, 6, 6, 8, 8, 10, 10, 12, 12, 14, 14, 16, 16, 18, 18, 20, 20, 22, 22, 24, 24, 26, 26, 28, 0, 28 ],
				"width": 97,
				"height": 54
			}
		},
		"6": {
			"3": { "x": 6.95, "y": 8.87, "scaleX": -0.976, "rotation": 178.2, "width": 33, "height": 35 }
		},
		"bottom": {
			"bottom": { "x": -0.36, "y": -3.89, "width": 449, "height": 105 }
		},
		"bottom_back": {
			"bottom_back": { "x": -8.13, "y": -1.46, "width": 434, "height": 20 }
		},
		"flag": {
			"flag": {
				"type": "mesh",
				"uvs": [ 0.35668, 0.04753, 0.26095, 0.11883, 0.23919, 0.19933, 0.22614, 0.29593, 0.30446, 0.35113, 0.36538, 0.44083, 0.34363, 0.54433, 0.32622, 0.62483, 0.24355, 0.68693, 0.11301, 0.73523, 0.06514, 0.80653, 0.01293, 0.91693, 0, 1, 0.13041, 1, 0.30446, 0.98363, 0.435, 0.90083, 0.50898, 0.79043, 0.61341, 0.69153, 0.70479, 0.63173, 0.7483, 0.56273, 0.78311, 0.50523, 0.84403, 0.41553, 0.80922, 0.34883, 0.84403, 0.27753, 0.93976, 0.16253, 1, 0.08893, 1, 0.01993, 0.83533, 0, 0.53073, 0, 0.58678, 0.17523, 0.55889, 0.3116, 0.54494, 0.4664, 0.48218, 0.63594, 0.37061, 0.776, 0.21721, 0.89762 ],
				"triangles": [ 10, 9, 34, 14, 34, 33, 11, 10, 34, 13, 11, 34, 13, 34, 14, 12, 11, 13, 33, 32, 16, 34, 8, 33, 15, 33, 16, 15, 14, 33, 8, 7, 33, 16, 32, 17, 34, 9, 8, 18, 31, 19, 17, 32, 31, 32, 6, 31, 7, 6, 32, 18, 17, 31, 33, 7, 32, 5, 4, 30, 31, 5, 30, 31, 30, 22, 20, 31, 22, 20, 22, 21, 19, 31, 20, 31, 6, 5, 27, 26, 25, 24, 27, 25, 29, 28, 27, 23, 29, 27, 24, 23, 27, 29, 0, 28, 22, 30, 29, 30, 0, 29, 23, 22, 29, 0, 2, 1, 30, 2, 0, 30, 4, 2, 3, 2, 4 ],
				"vertices": [ 2, 8, -14.71, -21.1, 0.99934, 9, -33.78, -20.36, 6.6E-4, 2, 8, -4.31, -26.42, 0.97291, 9, -23.5, -25.91, 0.02709, 2, 8, 6.56, -26.39, 0.87037, 9, -12.64, -26.12, 0.12963, 2, 8, 19.47, -25.45, 0.61765, 9, 0.29, -25.46, 0.38235, 3, 8, 25.97, -18.91, 0.34977, 9, 6.93, -19.07, 0.64091, 10, -14.13, -19.73, 0.00932, 3, 8, 37.21, -12.93, 0.0207, 9, 18.3, -13.33, 0.66703, 10, -3.03, -13.48, 0.31227, 3, 9, 32.22, -13.17, 0.02177, 10, 10.86, -12.69, 0.92677, 11, -4.54, -16.32, 0.05146, 2, 10, 21.67, -12.11, 0.4132, 11, 4.93, -11.07, 0.5868, 3, 10, 30.83, -16.48, 0.02489, 11, 15.07, -11, 0.92399, 12, -0.52, -11.67, 0.05112, 3, 11, 25.68, -14.75, 0.40369, 12, 10.44, -14.21, 0.5818, 13, -11.34, -11.44, 0.01452, 3, 11, 35.4, -11.96, 0.08295, 12, 19.79, -10.35, 0.49942, 13, -1.28, -10.42, 0.41763, 1, 13, 13.63, -7.44, 1, 1, 13, 24.06, -3.51, 1, 2, 12, 35.92, 10.37, 0.00445, 13, 20.11, 4.81, 0.99555, 2, 12, 26.07, 18.05, 0.1752, 13, 12.87, 14.99, 0.8248, 2, 12, 11.68, 17.5, 0.69938, 13, -1.07, 18.58, 0.30062, 3, 11, 15.43, 12.3, 0.24859, 12, -2.78, 11.51, 0.74559, 13, -16.64, 16.99, 0.00582, 3, 10, 27.08, 9.38, 0.33148, 11, 0.39, 10.62, 0.62478, 12, -17.54, 8.15, 0.04374, 3, 9, 40.69, 13.58, 0.01206, 10, 18.12, 14.41, 0.90554, 11, -9.87, 11.23, 0.08239, 2, 9, 31.17, 15.5, 0.1797, 10, 8.52, 15.9, 0.8203, 3, 8, 41.48, 17.51, 6.0E-5, 9, 23.24, 17, 0.54661, 10, 0.53, 17.04, 0.45333, 3, 8, 29, 20.04, 0.06231, 9, 10.82, 19.81, 0.88419, 10, -12, 19.29, 0.0535, 3, 8, 20.53, 16.32, 0.34953, 9, 2.27, 16.28, 0.6492, 10, -20.38, 15.37, 0.00128, 2, 8, 10.75, 17.39, 0.84102, 9, -7.48, 17.56, 0.15898, 2, 8, -5.43, 21.87, 0.99999, 9, -23.56, 22.39, 1.0E-5, 1, 8, -15.77, 24.66, 1, 1, 8, -24.9, 23.33, 1, 1, 8, -25.86, 11.44, 1, 1, 8, -22.76, -9.85, 1, 1, 8, -0.16, -2.56, 1, 2, 8, 18.16, -1.89, 0.63804, 9, -0.5, -1.88, 0.36196, 1, 9, 20.15, -0.33, 1, 2, 10, 21.3, -1, 0.70254, 11, -0.27, -1.24, 0.29746, 2, 12, 2.32, 2.96, 0.99821, 13, -14.2, 7.33, 0.00179, 2, 12, 21.65, 5.78, 0.14911, 13, 5.13, 4.5, 0.85089 ],
				"hull": 29,
				"edges": [ 0, 2, 2, 4, 4, 6, 6, 8, 8, 10, 10, 12, 12, 14, 14, 16, 16, 18, 18, 20, 20, 22, 22, 24, 24, 26, 26, 28, 28, 30, 30, 32, 32, 34, 34, 36, 36, 38, 38, 40, 40, 42, 42, 44, 44, 46, 46, 48, 48, 50, 50, 52, 52, 54, 54, 56, 0, 56 ],
				"width": 37,
				"height": 70
			}
		},
		"gear-02": {
			"gear-02": { "x": -0.75, "y": 2.58, "width": 103, "height": 105 }
		},
		"gear-3": {
			"gear-01": { "x": 1.15, "y": 3.93, "width": 134, "height": 135 }
		},
		"gear-4": {
			"gear-02": { "x": -0.75, "y": 2.58, "width": 103, "height": 105 }
		},
		"gear-5": {
			"gear-01": { "x": 1.15, "y": 3.93, "width": 134, "height": 135 }
		},
		"top": {
			"top": { "x": -1.8, "y": 402.62, "scaleX": 1.044, "scaleY": 1.044, "width": 376, "height": 859 }
		},
		"wheel2": {
			"wheel": { "x": -0.56, "y": 2.04, "width": 99, "height": 99 }
		},
		"wheel3": {
			"wheel": { "x": -0.95, "y": 1.75, "width": 99, "height": 99 }
		}
	}
},
"animations": {
	"Idle": {
		"bones": {
			"bottom": {
				"rotate": [
					{ "time": 0, "angle": 0, "curve": "stepped" },
					{ "time": 0.0333, "angle": 0 }
				],
				"translate": [
					{ "time": 0, "x": 0, "y": 0, "curve": "stepped" },
					{ "time": 0.0333, "x": 0, "y": 0 }
				],
				"scale": [
					{ "time": 0, "x": 1, "y": 1, "curve": "stepped" },
					{ "time": 0.0333, "x": 1, "y": 1 }
				],
				"shear": [
					{ "time": 0, "x": 0, "y": 0, "curve": "stepped" },
					{ "time": 0.0333, "x": 0, "y": 0 }
				]
			},
			"wheel2": {
				"rotate": [
					{ "time": 0, "angle": 0, "curve": "stepped" },
					{ "time": 0.0333, "angle": 0 }
				],
				"translate": [
					{ "time": 0, "x": 0, "y": 0, "curve": "stepped" },
					{ "time": 0.0333, "x": 0, "y": 0 }
				],
				"scale": [
					{ "time": 0, "x": 1, "y": 1, "curve": "stepped" },
					{ "time": 0.0333, "x": 1, "y": 1 }
				],
				"shear": [
					{ "time": 0, "x": 0, "y": 0, "curve": "stepped" },
					{ "time": 0.0333, "x": 0, "y": 0 }
				]
			},
			"wheel3": {
				"rotate": [
					{ "time": 0, "angle": 0, "curve": "stepped" },
					{ "time": 0.0333, "angle": 0 }
				],
				"translate": [
					{ "time": 0, "x": 0, "y": 0, "curve": "stepped" },
					{ "time": 0.0333, "x": 0, "y": 0 }
				],
				"scale": [
					{ "time": 0, "x": 1, "y": 1, "curve": "stepped" },
					{ "time": 0.0333, "x": 1, "y": 1 }
				],
				"shear": [
					{ "time": 0, "x": 0, "y": 0, "curve": "stepped" },
					{ "time": 0.0333, "x": 0, "y": 0 }
				]
			},
			"gear-02": {
				"rotate": [
					{ "time": 0, "angle": 0, "curve": "stepped" },
					{ "time": 0.0333, "angle": 0 }
				],
				"translate": [
					{ "time": 0, "x": 0, "y": 0, "curve": "stepped" },
					{ "time": 0.0333, "x": 0, "y": 0 }
				],
				"scale": [
					{ "time": 0, "x": 1, "y": 1, "curve": "stepped" },
					{ "time": 0.0333, "x": 1, "y": 1 }
				],
				"shear": [
					{ "time": 0, "x": 0, "y": 0, "curve": "stepped" },
					{ "time": 0.0333, "x": 0, "y": 0 }
				]
			},
			"gear-3": {
				"rotate": [
					{ "time": 0, "angle": 0, "curve": "stepped" },
					{ "time": 0.0333, "angle": 0 }
				],
				"translate": [
					{ "time": 0, "x": 0, "y": 0, "curve": "stepped" },
					{ "time": 0.0333, "x": 0, "y": 0 }
				],
				"scale": [
					{ "time": 0, "x": 1, "y": 1, "curve": "stepped" },
					{ "time": 0.0333, "x": 1, "y": 1 }
				],
				"shear": [
					{ "time": 0, "x": 0, "y": 0, "curve": "stepped" },
					{ "time": 0.0333, "x": 0, "y": 0 }
				]
			},
			"top": {
				"rotate": [
					{ "time": 0, "angle": 0, "curve": "stepped" },
					{ "time": 0.0333, "angle": 0 }
				],
				"translate": [
					{ "time": 0, "x": 0, "y": 0, "curve": "stepped" },
					{ "time": 0.0333, "x": 0, "y": 0 }
				],
				"scale": [
					{ "time": 0, "x": 1, "y": 1, "curve": "stepped" },
					{ "time": 0.0333, "x": 1, "y": 1 }
				],
				"shear": [
					{ "time": 0, "x": 0, "y": 0, "curve": "stepped" },
					{ "time": 0.0333, "x": 0, "y": 0 }
				]
			},
			"flag3": {
				"rotate": [
					{ "time": 0, "angle": 0, "curve": "stepped" },
					{ "time": 0.0333, "angle": 0 }
				],
				"translate": [
					{ "time": 0, "x": 0, "y": 0, "curve": "stepped" },
					{ "time": 0.0333, "x": 0, "y": 0 }
				],
				"scale": [
					{ "time": 0, "x": 1, "y": 1, "curve": "stepped" },
					{ "time": 0.0333, "x": 1, "y": 1 }
				],
				"shear": [
					{ "time": 0, "x": 0, "y": 0, "curve": "stepped" },
					{ "time": 0.0333, "x": 0, "y": 0 }
				]
			},
			"flag4": {
				"rotate": [
					{ "time": 0, "angle": 0, "curve": "stepped" },
					{ "time": 0.0333, "angle": 0 }
				],
				"translate": [
					{ "time": 0, "x": 0, "y": 0, "curve": "stepped" },
					{ "time": 0.0333, "x": 0, "y": 0 }
				],
				"scale": [
					{ "time": 0, "x": 1, "y": 1, "curve": "stepped" },
					{ "time": 0.0333, "x": 1, "y": 1 }
				],
				"shear": [
					{ "time": 0, "x": 0, "y": 0, "curve": "stepped" },
					{ "time": 0.0333, "x": 0, "y": 0 }
				]
			},
			"flag5": {
				"rotate": [
					{ "time": 0, "angle": 0, "curve": "stepped" },
					{ "time": 0.0333, "angle": 0 }
				],
				"translate": [
					{ "time": 0, "x": 0, "y": 0, "curve": "stepped" },
					{ "time": 0.0333, "x": 0, "y": 0 }
				],
				"scale": [
					{ "time": 0, "x": 1, "y": 1, "curve": "stepped" },
					{ "time": 0.0333, "x": 1, "y": 1 }
				],
				"shear": [
					{ "time": 0, "x": 0, "y": 0, "curve": "stepped" },
					{ "time": 0.0333, "x": 0, "y": 0 }
				]
			},
			"flag7": {
				"rotate": [
					{ "time": 0, "angle": 0, "curve": "stepped" },
					{ "time": 0.0333, "angle": 0 }
				],
				"translate": [
					{ "time": 0, "x": 0, "y": 0, "curve": "stepped" },
					{ "time": 0.0333, "x": 0, "y": 0 }
				],
				"scale": [
					{ "time": 0, "x": 1, "y": 1, "curve": "stepped" },
					{ "time": 0.0333, "x": 1, "y": 1 }
				],
				"shear": [
					{ "time": 0, "x": 0, "y": 0, "curve": "stepped" },
					{ "time": 0.0333, "x": 0, "y": 0 }
				]
			},
			"flag8": {
				"rotate": [
					{ "time": 0, "angle": 0, "curve": "stepped" },
					{ "time": 0.0333, "angle": 0 }
				],
				"translate": [
					{ "time": 0, "x": 0, "y": 0, "curve": "stepped" },
					{ "time": 0.0333, "x": 0, "y": 0 }
				],
				"scale": [
					{ "time": 0, "x": 1, "y": 1, "curve": "stepped" },
					{ "time": 0.0333, "x": 1, "y": 1 }
				],
				"shear": [
					{ "time": 0, "x": 0, "y": 0, "curve": "stepped" },
					{ "time": 0.0333, "x": 0, "y": 0 }
				]
			},
			"flag6": {
				"rotate": [
					{ "time": 0, "angle": 0, "curve": "stepped" },
					{ "time": 0.0333, "angle": 0 }
				],
				"translate": [
					{ "time": 0, "x": 0, "y": 0, "curve": "stepped" },
					{ "time": 0.0333, "x": 0, "y": 0 }
				],
				"scale": [
					{ "time": 0, "x": 1, "y": 1, "curve": "stepped" },
					{ "time": 0.0333, "x": 1, "y": 1 }
				],
				"shear": [
					{ "time": 0, "x": 0, "y": 0, "curve": "stepped" },
					{ "time": 0.0333, "x": 0, "y": 0 }
				]
			},
			"gear-4": {
				"rotate": [
					{ "time": 0, "angle": 0, "curve": "stepped" },
					{ "time": 0.0333, "angle": 0 }
				],
				"translate": [
					{ "time": 0, "x": 0, "y": 0, "curve": "stepped" },
					{ "time": 0.0333, "x": 0, "y": 0 }
				],
				"scale": [
					{ "time": 0, "x": 1, "y": 1, "curve": "stepped" },
					{ "time": 0.0333, "x": 1, "y": 1 }
				],
				"shear": [
					{ "time": 0, "x": 0, "y": 0, "curve": "stepped" },
					{ "time": 0.0333, "x": 0, "y": 0 }
				]
			},
			"gear-5": {
				"rotate": [
					{ "time": 0, "angle": 0, "curve": "stepped" },
					{ "time": 0.0333, "angle": 0 }
				],
				"translate": [
					{ "time": 0, "x": 0, "y": 0, "curve": "stepped" },
					{ "time": 0.0333, "x": 0, "y": 0 }
				],
				"scale": [
					{ "time": 0, "x": 1, "y": 1, "curve": "stepped" },
					{ "time": 0.0333, "x": 1, "y": 1 }
				],
				"shear": [
					{ "time": 0, "x": 0, "y": 0, "curve": "stepped" },
					{ "time": 0.0333, "x": 0, "y": 0 }
				]
			}
		}
	},
	"drag_left": {
		"bones": {
			"bottom": {
				"rotate": [
					{ "time": 0, "angle": 0 }
				],
				"translate": [
					{
						"time": 0,
						"x": 0,
						"y": 0,
						"curve": [ 0.25, 0, 0.75, 1 ]
					},
					{ "time": 1, "x": -433.6, "y": 0 }
				],
				"scale": [
					{ "time": 0, "x": 1, "y": 1 }
				],
				"shear": [
					{ "time": 0, "x": 0, "y": 0 }
				]
			},
			"wheel2": {
				"rotate": [
					{ "time": 0, "angle": 0 }
				],
				"translate": [
					{ "time": 0, "x": 0, "y": 0 }
				],
				"scale": [
					{ "time": 0, "x": 1, "y": 1 }
				],
				"shear": [
					{ "time": 0, "x": 0, "y": 0 }
				]
			},
			"wheel3": {
				"rotate": [
					{ "time": 0, "angle": 0 }
				],
				"translate": [
					{ "time": 0, "x": 0, "y": 0 }
				],
				"scale": [
					{ "time": 0, "x": 1, "y": 1 }
				],
				"shear": [
					{ "time": 0, "x": 0, "y": 0 }
				]
			},
			"top": {
				"rotate": [
					{
						"time": 0,
						"angle": 0,
						"curve": [ 0.25, 0, 0.75, 1 ]
					},
					{
						"time": 0.3333,
						"angle": -5.75,
						"curve": [ 0.25, 0, 0.75, 1 ]
					},
					{ "time": 1, "angle": 0 }
				],
				"translate": [
					{ "time": 0, "x": 0, "y": 0, "curve": "stepped" },
					{ "time": 1, "x": 0, "y": 0 }
				],
				"scale": [
					{ "time": 0, "x": 1, "y": 1, "curve": "stepped" },
					{ "time": 1, "x": 1, "y": 1 }
				],
				"shear": [
					{ "time": 0, "x": 0, "y": 0, "curve": "stepped" },
					{ "time": 1, "x": 0, "y": 0 }
				]
			},
			"flag3": {
				"rotate": [
					{ "time": 0, "angle": 0 },
					{ "time": 0.2, "angle": 17.21 },
					{ "time": 0.6, "angle": 44.96 },
					{ "time": 1, "angle": 0 }
				],
				"translate": [
					{ "time": 0, "x": 0, "y": 0, "curve": "stepped" },
					{ "time": 1, "x": 0, "y": 0 }
				],
				"scale": [
					{ "time": 0, "x": 1, "y": 1, "curve": "stepped" },
					{ "time": 1, "x": 1, "y": 1 }
				],
				"shear": [
					{ "time": 0, "x": 0, "y": 0, "curve": "stepped" },
					{ "time": 1, "x": 0, "y": 0 }
				]
			},
			"flag4": {
				"rotate": [
					{ "time": 0, "angle": 0 },
					{ "time": 0.2, "angle": -17.37 },
					{ "time": 0.6, "angle": 14.19 },
					{ "time": 1, "angle": 0 }
				],
				"translate": [
					{ "time": 0, "x": 0, "y": 0, "curve": "stepped" },
					{ "time": 1, "x": 0, "y": 0 }
				],
				"scale": [
					{ "time": 0, "x": 1, "y": 1, "curve": "stepped" },
					{ "time": 1, "x": 1, "y": 1 }
				],
				"shear": [
					{ "time": 0, "x": 0, "y": 0, "curve": "stepped" },
					{ "time": 1, "x": 0, "y": 0 }
				]
			},
			"flag5": {
				"rotate": [
					{ "time": 0, "angle": 0 },
					{ "time": 0.2, "angle": 3.47 },
					{ "time": 0.6, "angle": 15.37 },
					{ "time": 1, "angle": 0 }
				],
				"translate": [
					{ "time": 0, "x": 0, "y": 0, "curve": "stepped" },
					{ "time": 1, "x": 0, "y": 0 }
				],
				"scale": [
					{ "time": 0, "x": 1, "y": 1, "curve": "stepped" },
					{ "time": 1, "x": 1, "y": 1 }
				],
				"shear": [
					{ "time": 0, "x": 0, "y": 0, "curve": "stepped" },
					{ "time": 1, "x": 0, "y": 0 }
				]
			},
			"flag7": {
				"rotate": [
					{ "time": 0, "angle": 0 },
					{ "time": 0.2, "angle": 14.82 },
					{ "time": 0.6, "angle": 17.86 },
					{ "time": 1, "angle": 0 }
				],
				"translate": [
					{ "time": 0, "x": 0, "y": 0, "curve": "stepped" },
					{ "time": 1, "x": 0, "y": 0 }
				],
				"scale": [
					{ "time": 0, "x": 1, "y": 1, "curve": "stepped" },
					{ "time": 1, "x": 1, "y": 1 }
				],
				"shear": [
					{ "time": 0, "x": 0, "y": 0, "curve": "stepped" },
					{ "time": 1, "x": 0, "y": 0 }
				]
			},
			"flag8": {
				"rotate": [
					{ "time": 0, "angle": 0 },
					{ "time": 0.2, "angle": -14.75 },
					{ "time": 0.6, "angle": -14 },
					{ "time": 1, "angle": 0 }
				],
				"translate": [
					{ "time": 0, "x": 0, "y": 0, "curve": "stepped" },
					{ "time": 1, "x": 0, "y": 0 }
				],
				"scale": [
					{ "time": 0, "x": 1, "y": 1, "curve": "stepped" },
					{ "time": 1, "x": 1, "y": 1 }
				],
				"shear": [
					{ "time": 0, "x": 0, "y": 0, "curve": "stepped" },
					{ "time": 1, "x": 0, "y": 0 }
				]
			},
			"flag6": {
				"rotate": [
					{ "time": 0, "angle": 0 },
					{ "time": 0.2, "angle": 21.41 },
					{ "time": 0.6, "angle": 29.96 },
					{ "time": 1, "angle": 0 }
				],
				"translate": [
					{ "time": 0, "x": 0, "y": 0, "curve": "stepped" },
					{ "time": 1, "x": 0, "y": 0 }
				],
				"scale": [
					{ "time": 0, "x": 1, "y": 1, "curve": "stepped" },
					{ "time": 1, "x": 1, "y": 1 }
				],
				"shear": [
					{ "time": 0, "x": 0, "y": 0, "curve": "stepped" },
					{ "time": 1, "x": 0, "y": 0 }
				]
			}
		}
	},
	"drag_left_inplace": {
		"bones": {
			"bottom": {
				"rotate": [
					{ "time": 0, "angle": 0 }
				],
				"translate": [
					{ "time": 0, "x": 0, "y": 0 }
				],
				"scale": [
					{ "time": 0, "x": 1, "y": 1 }
				],
				"shear": [
					{ "time": 0, "x": 0, "y": 0 }
				]
			},
			"wheel2": {
				"rotate": [
					{ "time": 0, "angle": 0 }
				],
				"translate": [
					{ "time": 0, "x": 0, "y": 0 }
				],
				"scale": [
					{ "time": 0, "x": 1, "y": 1 }
				],
				"shear": [
					{ "time": 0, "x": 0, "y": 0 }
				]
			},
			"wheel3": {
				"rotate": [
					{ "time": 0, "angle": 0 }
				],
				"translate": [
					{ "time": 0, "x": 0, "y": 0 }
				],
				"scale": [
					{ "time": 0, "x": 1, "y": 1 }
				],
				"shear": [
					{ "time": 0, "x": 0, "y": 0 }
				]
			},
			"top": {
				"rotate": [
					{
						"time": 0,
						"angle": 0,
						"curve": [ 0.25, 0, 0.75, 1 ]
					},
					{
						"time": 0.3333,
						"angle": -5.75,
						"curve": [ 0.25, 0, 0.75, 1 ]
					},
					{ "time": 1, "angle": 0 }
				],
				"translate": [
					{ "time": 0, "x": 0, "y": 0, "curve": "stepped" },
					{ "time": 1, "x": 0, "y": 0 }
				],
				"scale": [
					{ "time": 0, "x": 1, "y": 1, "curve": "stepped" },
					{ "time": 1, "x": 1, "y": 1 }
				],
				"shear": [
					{ "time": 0, "x": 0, "y": 0, "curve": "stepped" },
					{ "time": 1, "x": 0, "y": 0 }
				]
			},
			"flag3": {
				"rotate": [
					{ "time": 0, "angle": 0 },
					{ "time": 0.2, "angle": 17.21 },
					{ "time": 0.6, "angle": 44.96 },
					{ "time": 1, "angle": 0 }
				],
				"translate": [
					{ "time": 0, "x": 0, "y": 0, "curve": "stepped" },
					{ "time": 1, "x": 0, "y": 0 }
				],
				"scale": [
					{ "time": 0, "x": 1, "y": 1, "curve": "stepped" },
					{ "time": 1, "x": 1, "y": 1 }
				],
				"shear": [
					{ "time": 0, "x": 0, "y": 0, "curve": "stepped" },
					{ "time": 1, "x": 0, "y": 0 }
				]
			},
			"flag4": {
				"rotate": [
					{ "time": 0, "angle": 0 },
					{ "time": 0.2, "angle": -17.37 },
					{ "time": 0.6, "angle": 14.19 },
					{ "time": 1, "angle": 0 }
				],
				"translate": [
					{ "time": 0, "x": 0, "y": 0, "curve": "stepped" },
					{ "time": 1, "x": 0, "y": 0 }
				],
				"scale": [
					{ "time": 0, "x": 1, "y": 1, "curve": "stepped" },
					{ "time": 1, "x": 1, "y": 1 }
				],
				"shear": [
					{ "time": 0, "x": 0, "y": 0, "curve": "stepped" },
					{ "time": 1, "x": 0, "y": 0 }
				]
			},
			"flag5": {
				"rotate": [
					{ "time": 0, "angle": 0 },
					{ "time": 0.2, "angle": 3.47 },
					{ "time": 0.6, "angle": 15.37 },
					{ "time": 1, "angle": 0 }
				],
				"translate": [
					{ "time": 0, "x": 0, "y": 0, "curve": "stepped" },
					{ "time": 1, "x": 0, "y": 0 }
				],
				"scale": [
					{ "time": 0, "x": 1, "y": 1, "curve": "stepped" },
					{ "time": 1, "x": 1, "y": 1 }
				],
				"shear": [
					{ "time": 0, "x": 0, "y": 0, "curve": "stepped" },
					{ "time": 1, "x": 0, "y": 0 }
				]
			},
			"flag7": {
				"rotate": [
					{ "time": 0, "angle": 0 },
					{ "time": 0.2, "angle": 14.82 },
					{ "time": 0.6, "angle": 17.86 },
					{ "time": 1, "angle": 0 }
				],
				"translate": [
					{ "time": 0, "x": 0, "y": 0, "curve": "stepped" },
					{ "time": 1, "x": 0, "y": 0 }
				],
				"scale": [
					{ "time": 0, "x": 1, "y": 1, "curve": "stepped" },
					{ "time": 1, "x": 1, "y": 1 }
				],
				"shear": [
					{ "time": 0, "x": 0, "y": 0, "curve": "stepped" },
					{ "time": 1, "x": 0, "y": 0 }
				]
			},
			"flag8": {
				"rotate": [
					{ "time": 0, "angle": 0 },
					{ "time": 0.2, "angle": -14.75 },
					{ "time": 0.6, "angle": -14 },
					{ "time": 1, "angle": 0 }
				],
				"translate": [
					{ "time": 0, "x": 0, "y": 0, "curve": "stepped" },
					{ "time": 1, "x": 0, "y": 0 }
				],
				"scale": [
					{ "time": 0, "x": 1, "y": 1, "curve": "stepped" },
					{ "time": 1, "x": 1, "y": 1 }
				],
				"shear": [
					{ "time": 0, "x": 0, "y": 0, "curve": "stepped" },
					{ "time": 1, "x": 0, "y": 0 }
				]
			},
			"flag6": {
				"rotate": [
					{ "time": 0, "angle": 0 },
					{ "time": 0.2, "angle": 21.41 },
					{ "time": 0.6, "angle": 29.96 },
					{ "time": 1, "angle": 0 }
				],
				"translate": [
					{ "time": 0, "x": 0, "y": 0, "curve": "stepped" },
					{ "time": 1, "x": 0, "y": 0 }
				],
				"scale": [
					{ "time": 0, "x": 1, "y": 1, "curve": "stepped" },
					{ "time": 1, "x": 1, "y": 1 }
				],
				"shear": [
					{ "time": 0, "x": 0, "y": 0, "curve": "stepped" },
					{ "time": 1, "x": 0, "y": 0 }
				]
			}
		}
	},
	"drag_right": {
		"bones": {
			"bottom": {
				"rotate": [
					{ "time": 0, "angle": 0 }
				],
				"translate": [
					{
						"time": 0,
						"x": 0,
						"y": 0,
						"curve": [ 0.25, 0, 0.75, 1 ]
					},
					{ "time": 1, "x": 505.76, "y": 0 }
				],
				"scale": [
					{ "time": 0, "x": 1, "y": 1 }
				],
				"shear": [
					{ "time": 0, "x": 0, "y": 0 }
				]
			},
			"wheel2": {
				"rotate": [
					{ "time": 0, "angle": 0 }
				],
				"translate": [
					{ "time": 0, "x": 0, "y": 0 }
				],
				"scale": [
					{ "time": 0, "x": 1, "y": 1 }
				],
				"shear": [
					{ "time": 0, "x": 0, "y": 0 }
				]
			},
			"wheel3": {
				"rotate": [
					{ "time": 0, "angle": 0 }
				],
				"translate": [
					{ "time": 0, "x": 0, "y": 0 }
				],
				"scale": [
					{ "time": 0, "x": 1, "y": 1 }
				],
				"shear": [
					{ "time": 0, "x": 0, "y": 0 }
				]
			},
			"top": {
				"rotate": [
					{
						"time": 0,
						"angle": 0,
						"curve": [ 0.595, 0, 0.75, 1 ]
					},
					{
						"time": 0.3333,
						"angle": 5.64,
						"curve": [ 0.595, 0, 0.75, 1 ]
					},
					{ "time": 1, "angle": 0 }
				],
				"translate": [
					{ "time": 0, "x": 0, "y": 0, "curve": "stepped" },
					{ "time": 1, "x": 0, "y": 0 }
				],
				"scale": [
					{ "time": 0, "x": 1, "y": 1, "curve": "stepped" },
					{ "time": 1, "x": 1, "y": 1 }
				],
				"shear": [
					{ "time": 0, "x": 0, "y": 0, "curve": "stepped" },
					{ "time": 1, "x": 0, "y": 0 }
				]
			},
			"flag3": {
				"rotate": [
					{ "time": 0, "angle": 0 },
					{ "time": 0.2, "angle": -29.25 },
					{ "time": 0.4333, "angle": -25.03 },
					{ "time": 0.6, "angle": -29.94 },
					{ "time": 1, "angle": 0 }
				],
				"translate": [
					{ "time": 0, "x": 0, "y": 0, "curve": "stepped" },
					{ "time": 1, "x": 0, "y": 0 }
				],
				"scale": [
					{ "time": 0, "x": 1, "y": 1, "curve": "stepped" },
					{ "time": 1, "x": 1, "y": 1 }
				],
				"shear": [
					{ "time": 0, "x": 0, "y": 0, "curve": "stepped" },
					{ "time": 1, "x": 0, "y": 0 }
				]
			},
			"flag4": {
				"rotate": [
					{ "time": 0, "angle": 0 },
					{ "time": 0.2, "angle": -2.75 },
					{ "time": 0.4333, "angle": -13.89 },
					{ "time": 0.6, "angle": -26.84 },
					{ "time": 1, "angle": 0 }
				],
				"translate": [
					{ "time": 0, "x": 0, "y": 0, "curve": "stepped" },
					{ "time": 1, "x": 0, "y": 0 }
				],
				"scale": [
					{ "time": 0, "x": 1, "y": 1, "curve": "stepped" },
					{ "time": 1, "x": 1, "y": 1 }
				],
				"shear": [
					{ "time": 0, "x": 0, "y": 0, "curve": "stepped" },
					{ "time": 1, "x": 0, "y": 0 }
				]
			},
			"flag5": {
				"rotate": [
					{ "time": 0, "angle": 0 },
					{ "time": 0.2, "angle": 18.09 },
					{ "time": 0.4333, "angle": -12.71 },
					{ "time": 0.6, "angle": -28.51 },
					{ "time": 1, "angle": 0 }
				],
				"translate": [
					{ "time": 0, "x": 0, "y": 0, "curve": "stepped" },
					{ "time": 1, "x": 0, "y": 0 }
				],
				"scale": [
					{ "time": 0, "x": 1, "y": 1, "curve": "stepped" },
					{ "time": 1, "x": 1, "y": 1 }
				],
				"shear": [
					{ "time": 0, "x": 0, "y": 0, "curve": "stepped" },
					{ "time": 1, "x": 0, "y": 0 }
				]
			},
			"flag7": {
				"rotate": [
					{ "time": 0, "angle": 0 },
					{ "time": 0.2, "angle": 29.44 },
					{ "time": 0.4333, "angle": -10.23 },
					{ "time": 0.6, "angle": -0.21 },
					{ "time": 1, "angle": 0 }
				],
				"translate": [
					{ "time": 0, "x": 0, "y": 0, "curve": "stepped" },
					{ "time": 1, "x": 0, "y": 0 }
				],
				"scale": [
					{ "time": 0, "x": 1, "y": 1, "curve": "stepped" },
					{ "time": 1, "x": 1, "y": 1 }
				],
				"shear": [
					{ "time": 0, "x": 0, "y": 0, "curve": "stepped" },
					{ "time": 1, "x": 0, "y": 0 }
				]
			},
			"flag8": {
				"rotate": [
					{ "time": 0, "angle": 0 },
					{ "time": 0.2, "angle": -0.13 },
					{ "time": 0.4333, "angle": -42.09 },
					{ "time": 0.6, "angle": -109.07 },
					{ "time": 1, "angle": 0 }
				],
				"translate": [
					{ "time": 0, "x": 0, "y": 0, "curve": "stepped" },
					{ "time": 1, "x": 0, "y": 0 }
				],
				"scale": [
					{ "time": 0, "x": 1, "y": 1, "curve": "stepped" },
					{ "time": 1, "x": 1, "y": 1 }
				],
				"shear": [
					{ "time": 0, "x": 0, "y": 0, "curve": "stepped" },
					{ "time": 1, "x": 0, "y": 0 }
				]
			},
			"flag6": {
				"rotate": [
					{ "time": 0, "angle": 0 },
					{ "time": 0.2, "angle": 36.03 },
					{ "time": 0.4333, "angle": 1.87 },
					{ "time": 0.6, "angle": -5.31 },
					{ "time": 1, "angle": 0 }
				],
				"translate": [
					{ "time": 0, "x": 0, "y": 0, "curve": "stepped" },
					{ "time": 1, "x": 0, "y": 0 }
				],
				"scale": [
					{ "time": 0, "x": 1, "y": 1, "curve": "stepped" },
					{ "time": 1, "x": 1, "y": 1 }
				],
				"shear": [
					{ "time": 0, "x": 0, "y": 0, "curve": "stepped" },
					{ "time": 1, "x": 0, "y": 0 }
				]
			}
		}
	},
	"drag_right_inplace": {
		"bones": {
			"bottom": {
				"rotate": [
					{ "time": 0, "angle": 0 }
				],
				"translate": [
					{ "time": 0, "x": 0, "y": 0 }
				],
				"scale": [
					{ "time": 0, "x": 1, "y": 1 }
				],
				"shear": [
					{ "time": 0, "x": 0, "y": 0 }
				]
			},
			"wheel2": {
				"rotate": [
					{ "time": 0, "angle": 0 }
				],
				"translate": [
					{ "time": 0, "x": 0, "y": 0 }
				],
				"scale": [
					{ "time": 0, "x": 1, "y": 1 }
				],
				"shear": [
					{ "time": 0, "x": 0, "y": 0 }
				]
			},
			"wheel3": {
				"rotate": [
					{ "time": 0, "angle": 0 }
				],
				"translate": [
					{ "time": 0, "x": 0, "y": 0 }
				],
				"scale": [
					{ "time": 0, "x": 1, "y": 1 }
				],
				"shear": [
					{ "time": 0, "x": 0, "y": 0 }
				]
			},
			"top": {
				"rotate": [
					{
						"time": 0,
						"angle": 0,
						"curve": [ 0.595, 0, 0.75, 1 ]
					},
					{
						"time": 0.3333,
						"angle": 5.64,
						"curve": [ 0.595, 0, 0.75, 1 ]
					},
					{ "time": 1, "angle": 0 }
				],
				"translate": [
					{ "time": 0, "x": 0, "y": 0, "curve": "stepped" },
					{ "time": 1, "x": 0, "y": 0 }
				],
				"scale": [
					{ "time": 0, "x": 1, "y": 1, "curve": "stepped" },
					{ "time": 1, "x": 1, "y": 1 }
				],
				"shear": [
					{ "time": 0, "x": 0, "y": 0, "curve": "stepped" },
					{ "time": 1, "x": 0, "y": 0 }
				]
			},
			"flag3": {
				"rotate": [
					{ "time": 0, "angle": 0 },
					{ "time": 0.2, "angle": -29.25 },
					{ "time": 0.4333, "angle": -25.03 },
					{ "time": 0.6, "angle": -29.94 },
					{ "time": 1, "angle": 0 }
				],
				"translate": [
					{ "time": 0, "x": 0, "y": 0, "curve": "stepped" },
					{ "time": 1, "x": 0, "y": 0 }
				],
				"scale": [
					{ "time": 0, "x": 1, "y": 1, "curve": "stepped" },
					{ "time": 1, "x": 1, "y": 1 }
				],
				"shear": [
					{ "time": 0, "x": 0, "y": 0, "curve": "stepped" },
					{ "time": 1, "x": 0, "y": 0 }
				]
			},
			"flag4": {
				"rotate": [
					{ "time": 0, "angle": 0 },
					{ "time": 0.2, "angle": -2.75 },
					{ "time": 0.4333, "angle": -13.89 },
					{ "time": 0.6, "angle": -26.84 },
					{ "time": 1, "angle": 0 }
				],
				"translate": [
					{ "time": 0, "x": 0, "y": 0, "curve": "stepped" },
					{ "time": 1, "x": 0, "y": 0 }
				],
				"scale": [
					{ "time": 0, "x": 1, "y": 1, "curve": "stepped" },
					{ "time": 1, "x": 1, "y": 1 }
				],
				"shear": [
					{ "time": 0, "x": 0, "y": 0, "curve": "stepped" },
					{ "time": 1, "x": 0, "y": 0 }
				]
			},
			"flag5": {
				"rotate": [
					{ "time": 0, "angle": 0 },
					{ "time": 0.2, "angle": 18.09 },
					{ "time": 0.4333, "angle": -12.71 },
					{ "time": 0.6, "angle": -28.51 },
					{ "time": 1, "angle": 0 }
				],
				"translate": [
					{ "time": 0, "x": 0, "y": 0, "curve": "stepped" },
					{ "time": 1, "x": 0, "y": 0 }
				],
				"scale": [
					{ "time": 0, "x": 1, "y": 1, "curve": "stepped" },
					{ "time": 1, "x": 1, "y": 1 }
				],
				"shear": [
					{ "time": 0, "x": 0, "y": 0, "curve": "stepped" },
					{ "time": 1, "x": 0, "y": 0 }
				]
			},
			"flag7": {
				"rotate": [
					{ "time": 0, "angle": 0 },
					{ "time": 0.2, "angle": 29.44 },
					{ "time": 0.4333, "angle": -10.23 },
					{ "time": 0.6, "angle": -0.21 },
					{ "time": 1, "angle": 0 }
				],
				"translate": [
					{ "time": 0, "x": 0, "y": 0, "curve": "stepped" },
					{ "time": 1, "x": 0, "y": 0 }
				],
				"scale": [
					{ "time": 0, "x": 1, "y": 1, "curve": "stepped" },
					{ "time": 1, "x": 1, "y": 1 }
				],
				"shear": [
					{ "time": 0, "x": 0, "y": 0, "curve": "stepped" },
					{ "time": 1, "x": 0, "y": 0 }
				]
			},
			"flag8": {
				"rotate": [
					{ "time": 0, "angle": 0 },
					{ "time": 0.2, "angle": -0.13 },
					{ "time": 0.4333, "angle": -42.09 },
					{ "time": 0.6, "angle": -109.07 },
					{ "time": 1, "angle": 0 }
				],
				"translate": [
					{ "time": 0, "x": 0, "y": 0, "curve": "stepped" },
					{ "time": 1, "x": 0, "y": 0 }
				],
				"scale": [
					{ "time": 0, "x": 1, "y": 1, "curve": "stepped" },
					{ "time": 1, "x": 1, "y": 1 }
				],
				"shear": [
					{ "time": 0, "x": 0, "y": 0, "curve": "stepped" },
					{ "time": 1, "x": 0, "y": 0 }
				]
			},
			"flag6": {
				"rotate": [
					{ "time": 0, "angle": 0 },
					{ "time": 0.2, "angle": 36.03 },
					{ "time": 0.4333, "angle": 1.87 },
					{ "time": 0.6, "angle": -5.31 },
					{ "time": 1, "angle": 0 }
				],
				"translate": [
					{ "time": 0, "x": 0, "y": 0, "curve": "stepped" },
					{ "time": 1, "x": 0, "y": 0 }
				],
				"scale": [
					{ "time": 0, "x": 1, "y": 1, "curve": "stepped" },
					{ "time": 1, "x": 1, "y": 1 }
				],
				"shear": [
					{ "time": 0, "x": 0, "y": 0, "curve": "stepped" },
					{ "time": 1, "x": 0, "y": 0 }
				]
			}
		}
	},
	"swaying_left": {
		"bones": {
			"bottom": {
				"rotate": [
					{ "time": 0, "angle": 0 }
				],
				"translate": [
					{ "time": 0, "x": 0, "y": 0 }
				],
				"scale": [
					{ "time": 0, "x": 1, "y": 1 }
				],
				"shear": [
					{ "time": 0, "x": 0, "y": 0 }
				]
			},
			"wheel2": {
				"rotate": [
					{ "time": 0, "angle": 0 }
				],
				"translate": [
					{ "time": 0, "x": 0, "y": 0 }
				],
				"scale": [
					{ "time": 0, "x": 1, "y": 1 }
				],
				"shear": [
					{ "time": 0, "x": 0, "y": 0 }
				]
			},
			"wheel3": {
				"rotate": [
					{ "time": 0, "angle": 0 }
				],
				"translate": [
					{ "time": 0, "x": 0, "y": 0 }
				],
				"scale": [
					{ "time": 0, "x": 1, "y": 1 }
				],
				"shear": [
					{ "time": 0, "x": 0, "y": 0 }
				]
			},
			"gear-02": {
				"rotate": [
					{ "time": 0, "angle": 0 }
				],
				"translate": [
					{ "time": 0, "x": 0, "y": 0 }
				],
				"scale": [
					{ "time": 0, "x": 1, "y": 1 }
				],
				"shear": [
					{ "time": 0, "x": 0, "y": 0 }
				]
			},
			"gear-3": {
				"rotate": [
					{ "time": 0, "angle": 0 }
				],
				"translate": [
					{ "time": 0, "x": 0, "y": 0 }
				],
				"scale": [
					{ "time": 0, "x": 1, "y": 1 }
				],
				"shear": [
					{ "time": 0, "x": 0, "y": 0 }
				]
			},
			"top": {
				"rotate": [
					{
						"time": 0,
						"angle": 0,
						"curve": [ 0.25, 0, 0.75, 1 ]
					},
					{
						"time": 0.2333,
						"angle": 3.21,
						"curve": [ 0.25, 0, 0.75, 1 ]
					},
					{
						"time": 0.5333,
						"angle": -2.38,
						"curve": [ 0.25, 0, 0.75, 1 ]
					},
					{
						"time": 0.8333,
						"angle": 1.42,
						"curve": [ 0.25, 0, 0.75, 1 ]
					},
					{
						"time": 1.0667,
						"angle": -1.19,
						"curve": [ 0.25, 0, 0.75, 1 ]
					},
					{ "time": 1.3333, "angle": 0 }
				],
				"translate": [
					{ "time": 0, "x": 0, "y": 0, "curve": "stepped" },
					{ "time": 1.3333, "x": 0, "y": 0 }
				],
				"scale": [
					{ "time": 0, "x": 1, "y": 1, "curve": "stepped" },
					{ "time": 1.3333, "x": 1, "y": 1 }
				],
				"shear": [
					{ "time": 0, "x": 0, "y": 0, "curve": "stepped" },
					{ "time": 1.3333, "x": 0, "y": 0 }
				]
			},
			"flag3": {
				"rotate": [
					{ "time": 0, "angle": 0 },
					{ "time": 0.2667, "angle": -29.25 },
					{ "time": 0.5667, "angle": -25.03 },
					{ "time": 0.8, "angle": -29.94 },
					{ "time": 1.3333, "angle": 0 }
				],
				"translate": [
					{ "time": 0, "x": 0, "y": 0, "curve": "stepped" },
					{ "time": 1.3333, "x": 0, "y": 0 }
				],
				"scale": [
					{ "time": 0, "x": 1, "y": 1, "curve": "stepped" },
					{ "time": 1.3333, "x": 1, "y": 1 }
				],
				"shear": [
					{ "time": 0, "x": 0, "y": 0, "curve": "stepped" },
					{ "time": 1.3333, "x": 0, "y": 0 }
				]
			},
			"flag4": {
				"rotate": [
					{ "time": 0, "angle": 0 },
					{ "time": 0.2667, "angle": -2.75 },
					{ "time": 0.5667, "angle": -13.89 },
					{ "time": 0.8, "angle": -26.84 },
					{ "time": 1.3333, "angle": 0 }
				],
				"translate": [
					{ "time": 0, "x": 0, "y": 0, "curve": "stepped" },
					{ "time": 1.3333, "x": 0, "y": 0 }
				],
				"scale": [
					{ "time": 0, "x": 1, "y": 1, "curve": "stepped" },
					{ "time": 1.3333, "x": 1, "y": 1 }
				],
				"shear": [
					{ "time": 0, "x": 0, "y": 0, "curve": "stepped" },
					{ "time": 1.3333, "x": 0, "y": 0 }
				]
			},
			"flag5": {
				"rotate": [
					{ "time": 0, "angle": 0 },
					{ "time": 0.2667, "angle": 18.09 },
					{ "time": 0.5667, "angle": -12.71 },
					{ "time": 0.8, "angle": -28.51 },
					{ "time": 1.3333, "angle": 0 }
				],
				"translate": [
					{ "time": 0, "x": 0, "y": 0, "curve": "stepped" },
					{ "time": 1.3333, "x": 0, "y": 0 }
				],
				"scale": [
					{ "time": 0, "x": 1, "y": 1, "curve": "stepped" },
					{ "time": 1.3333, "x": 1, "y": 1 }
				],
				"shear": [
					{ "time": 0, "x": 0, "y": 0, "curve": "stepped" },
					{ "time": 1.3333, "x": 0, "y": 0 }
				]
			},
			"flag7": {
				"rotate": [
					{ "time": 0, "angle": 0 },
					{ "time": 0.2667, "angle": 29.44 },
					{ "time": 0.5667, "angle": -10.23 },
					{ "time": 0.8, "angle": -0.21 },
					{ "time": 1.3333, "angle": 0 }
				],
				"translate": [
					{ "time": 0, "x": 0, "y": 0, "curve": "stepped" },
					{ "time": 1.3333, "x": 0, "y": 0 }
				],
				"scale": [
					{ "time": 0, "x": 1, "y": 1, "curve": "stepped" },
					{ "time": 1.3333, "x": 1, "y": 1 }
				],
				"shear": [
					{ "time": 0, "x": 0, "y": 0, "curve": "stepped" },
					{ "time": 1.3333, "x": 0, "y": 0 }
				]
			},
			"flag8": {
				"rotate": [
					{ "time": 0, "angle": 0 },
					{ "time": 0.2667, "angle": -0.13 },
					{ "time": 0.5667, "angle": -42.09 },
					{ "time": 0.8, "angle": -109.07 },
					{ "time": 1.3333, "angle": 0 }
				],
				"translate": [
					{ "time": 0, "x": 0, "y": 0, "curve": "stepped" },
					{ "time": 1.3333, "x": 0, "y": 0 }
				],
				"scale": [
					{ "time": 0, "x": 1, "y": 1, "curve": "stepped" },
					{ "time": 1.3333, "x": 1, "y": 1 }
				],
				"shear": [
					{ "time": 0, "x": 0, "y": 0, "curve": "stepped" },
					{ "time": 1.3333, "x": 0, "y": 0 }
				]
			},
			"flag6": {
				"rotate": [
					{ "time": 0, "angle": 0 },
					{ "time": 0.2667, "angle": 36.03 },
					{ "time": 0.5667, "angle": 1.87 },
					{ "time": 0.8, "angle": -5.31 },
					{ "time": 1.3333, "angle": 0 }
				],
				"translate": [
					{ "time": 0, "x": 0, "y": 0, "curve": "stepped" },
					{ "time": 1.3333, "x": 0, "y": 0 }
				],
				"scale": [
					{ "time": 0, "x": 1, "y": 1, "curve": "stepped" },
					{ "time": 1.3333, "x": 1, "y": 1 }
				],
				"shear": [
					{ "time": 0, "x": 0, "y": 0, "curve": "stepped" },
					{ "time": 1.3333, "x": 0, "y": 0 }
				]
			},
			"gear-4": {
				"rotate": [
					{ "time": 0, "angle": 0 }
				],
				"translate": [
					{ "time": 0, "x": 0, "y": 0 }
				],
				"scale": [
					{ "time": 0, "x": 1, "y": 1 }
				],
				"shear": [
					{ "time": 0, "x": 0, "y": 0 }
				]
			},
			"gear-5": {
				"rotate": [
					{ "time": 0, "angle": 0 }
				],
				"translate": [
					{ "time": 0, "x": 0, "y": 0 }
				],
				"scale": [
					{ "time": 0, "x": 1, "y": 1 }
				],
				"shear": [
					{ "time": 0, "x": 0, "y": 0 }
				]
			}
		}
	},
	"swaying_right": {
		"bones": {
			"bottom": {
				"rotate": [
					{ "time": 0, "angle": 0 }
				],
				"translate": [
					{ "time": 0, "x": 0, "y": 0 }
				],
				"scale": [
					{ "time": 0, "x": 1, "y": 1 }
				],
				"shear": [
					{ "time": 0, "x": 0, "y": 0 }
				]
			},
			"wheel2": {
				"rotate": [
					{ "time": 0, "angle": 0 }
				],
				"translate": [
					{ "time": 0, "x": 0, "y": 0 }
				],
				"scale": [
					{ "time": 0, "x": 1, "y": 1 }
				],
				"shear": [
					{ "time": 0, "x": 0, "y": 0 }
				]
			},
			"wheel3": {
				"rotate": [
					{ "time": 0, "angle": 0 }
				],
				"translate": [
					{ "time": 0, "x": 0, "y": 0 }
				],
				"scale": [
					{ "time": 0, "x": 1, "y": 1 }
				],
				"shear": [
					{ "time": 0, "x": 0, "y": 0 }
				]
			},
			"gear-02": {
				"rotate": [
					{ "time": 0, "angle": 0 }
				],
				"translate": [
					{ "time": 0, "x": 0, "y": 0 }
				],
				"scale": [
					{ "time": 0, "x": 1, "y": 1 }
				],
				"shear": [
					{ "time": 0, "x": 0, "y": 0 }
				]
			},
			"gear-3": {
				"rotate": [
					{ "time": 0, "angle": 0 }
				],
				"translate": [
					{ "time": 0, "x": 0, "y": 0 }
				],
				"scale": [
					{ "time": 0, "x": 1, "y": 1 }
				],
				"shear": [
					{ "time": 0, "x": 0, "y": 0 }
				]
			},
			"top": {
				"rotate": [
					{
						"time": 0,
						"angle": 0,
						"curve": [ 0.25, 0, 0.75, 1 ]
					},
					{
						"time": 0.2667,
						"angle": -3.51,
						"curve": [ 0.25, 0, 0.75, 1 ]
					},
					{
						"time": 0.5333,
						"angle": 1.03,
						"curve": [ 0.25, 0, 0.75, 1 ]
					},
					{
						"time": 0.8,
						"angle": -2.21,
						"curve": [ 0.25, 0, 0.75, 1 ]
					},
					{
						"time": 1.1,
						"angle": 0.9,
						"curve": [ 0.25, 0, 0.75, 1 ]
					},
					{ "time": 1.3333, "angle": 0 }
				],
				"translate": [
					{ "time": 0, "x": 0, "y": 0, "curve": "stepped" },
					{ "time": 1.3333, "x": 0, "y": 0 }
				],
				"scale": [
					{ "time": 0, "x": 1, "y": 1, "curve": "stepped" },
					{ "time": 1.3333, "x": 1, "y": 1 }
				],
				"shear": [
					{ "time": 0, "x": 0, "y": 0, "curve": "stepped" },
					{ "time": 1.3333, "x": 0, "y": 0 }
				]
			},
			"flag3": {
				"rotate": [
					{ "time": 0, "angle": 0 },
					{ "time": 0.2667, "angle": 6.11 },
					{ "time": 0.8, "angle": 8.94 },
					{ "time": 1.3333, "angle": 0 }
				],
				"translate": [
					{ "time": 0, "x": 0, "y": 0, "curve": "stepped" },
					{ "time": 1.3333, "x": 0, "y": 0 }
				],
				"scale": [
					{ "time": 0, "x": 1, "y": 1, "curve": "stepped" },
					{ "time": 1.3333, "x": 1, "y": 1 }
				],
				"shear": [
					{ "time": 0, "x": 0, "y": 0, "curve": "stepped" },
					{ "time": 1.3333, "x": 0, "y": 0 }
				]
			},
			"flag4": {
				"rotate": [
					{ "time": 0, "angle": 0 },
					{ "time": 0.2667, "angle": -28.46 },
					{ "time": 0.8, "angle": 3.64 },
					{ "time": 1.3333, "angle": 0 }
				],
				"translate": [
					{ "time": 0, "x": 0, "y": 0, "curve": "stepped" },
					{ "time": 1.3333, "x": 0, "y": 0 }
				],
				"scale": [
					{ "time": 0, "x": 1, "y": 1, "curve": "stepped" },
					{ "time": 1.3333, "x": 1, "y": 1 }
				],
				"shear": [
					{ "time": 0, "x": 0, "y": 0, "curve": "stepped" },
					{ "time": 1.3333, "x": 0, "y": 0 }
				]
			},
			"flag5": {
				"rotate": [
					{ "time": 0, "angle": 0 },
					{ "time": 0.2667, "angle": -7.62 },
					{ "time": 0.8, "angle": 25.14 },
					{ "time": 1.3333, "angle": 0 }
				],
				"translate": [
					{ "time": 0, "x": 0, "y": 0, "curve": "stepped" },
					{ "time": 1.3333, "x": 0, "y": 0 }
				],
				"scale": [
					{ "time": 0, "x": 1, "y": 1, "curve": "stepped" },
					{ "time": 1.3333, "x": 1, "y": 1 }
				],
				"shear": [
					{ "time": 0, "x": 0, "y": 0, "curve": "stepped" },
					{ "time": 1.3333, "x": 0, "y": 0 }
				]
			},
			"flag7": {
				"rotate": [
					{ "time": 0, "angle": 0 },
					{ "time": 0.2667, "angle": 3.73 },
					{ "time": 0.8, "angle": 27.63 },
					{ "time": 1.3333, "angle": 0 }
				],
				"translate": [
					{ "time": 0, "x": 0, "y": 0, "curve": "stepped" },
					{ "time": 1.3333, "x": 0, "y": 0 }
				],
				"scale": [
					{ "time": 0, "x": 1, "y": 1, "curve": "stepped" },
					{ "time": 1.3333, "x": 1, "y": 1 }
				],
				"shear": [
					{ "time": 0, "x": 0, "y": 0, "curve": "stepped" },
					{ "time": 1.3333, "x": 0, "y": 0 }
				]
			},
			"flag8": {
				"rotate": [
					{ "time": 0, "angle": 0 },
					{ "time": 0.2667, "angle": -25.84 },
					{ "time": 0.8, "angle": -4.23 },
					{ "time": 1.3333, "angle": 0 }
				],
				"translate": [
					{ "time": 0, "x": 0, "y": 0, "curve": "stepped" },
					{ "time": 1.3333, "x": 0, "y": 0 }
				],
				"scale": [
					{ "time": 0, "x": 1, "y": 1, "curve": "stepped" },
					{ "time": 1.3333, "x": 1, "y": 1 }
				],
				"shear": [
					{ "time": 0, "x": 0, "y": 0, "curve": "stepped" },
					{ "time": 1.3333, "x": 0, "y": 0 }
				]
			},
			"flag6": {
				"rotate": [
					{ "time": 0, "angle": 0 },
					{ "time": 0.2667, "angle": 10.32 },
					{ "time": 0.8, "angle": 39.73 },
					{ "time": 1.3333, "angle": 0 }
				],
				"translate": [
					{ "time": 0, "x": 0, "y": 0, "curve": "stepped" },
					{ "time": 1.3333, "x": 0, "y": 0 }
				],
				"scale": [
					{ "time": 0, "x": 1, "y": 1, "curve": "stepped" },
					{ "time": 1.3333, "x": 1, "y": 1 }
				],
				"shear": [
					{ "time": 0, "x": 0, "y": 0, "curve": "stepped" },
					{ "time": 1.3333, "x": 0, "y": 0 }
				]
			},
			"gear-4": {
				"rotate": [
					{ "time": 0, "angle": 0 }
				],
				"translate": [
					{ "time": 0, "x": 0, "y": 0 }
				],
				"scale": [
					{ "time": 0, "x": 1, "y": 1 }
				],
				"shear": [
					{ "time": 0, "x": 0, "y": 0 }
				]
			},
			"gear-5": {
				"rotate": [
					{ "time": 0, "angle": 0 }
				],
				"translate": [
					{ "time": 0, "x": 0, "y": 0 }
				],
				"scale": [
					{ "time": 0, "x": 1, "y": 1 }
				],
				"shear": [
					{ "time": 0, "x": 0, "y": 0 }
				]
			}
		}
	}
}
}